findpath/__init__.py
findpath/findpath.py
findpath-1.0.2.dist-info/METADATA
findpath-1.0.2.dist-info/WHEEL
findpath-1.0.2.dist-info/licenses/LICENSE
findpath-1.0.2.dist-info/RECORD
