Metadata-Version: 2.4
Name: findpath
Version: 1.0.2
Summary: FindPath is a Python utility class designed to dynamically search for a specific file within a given directory structure.
Project-URL: Homepage, https://github.com/joshikarthikey/findpath
Project-URL: Issues, https://github.com/joshikarthikey/findpath/issues
Author-email: Karthikey <karthikey.cse@gmail.com>
License-Expression: MIT
License-File: LICENSE
Classifier: Operating System :: OS Independent
Classifier: Programming Language :: Python :: 3
Requires-Python: >=3.9
